ctxprotocol/__init__.py
ctxprotocol/py.typed
ctxprotocol/auth/__init__.py
ctxprotocol/client/__init__.py
ctxprotocol/client/client.py
ctxprotocol/client/types.py
ctxprotocol/client/resources/__init__.py
ctxprotocol/client/resources/discovery.py
ctxprotocol/client/resources/tools.py
ctxprotocol/context/__init__.py
ctxprotocol/context/hyperliquid.py
ctxprotocol/context/polymarket.py
ctxprotocol/context/wallet.py
ctxprotocol/handshake/__init__.py
ctxprotocol-0.5.7.dist-info/METADATA
ctxprotocol-0.5.7.dist-info/WHEEL
ctxprotocol-0.5.7.dist-info/RECORD
