Metadata-Version: 2.4
Name: ctxprotocol
Version: 0.5.7
Summary: Official Python SDK for the Context Protocol - Discover and execute AI tools programmatically
Project-URL: Homepage, https://ctxprotocol.com
Project-URL: Documentation, https://docs.ctxprotocol.com
Project-URL: Repository, https://github.com/ctxprotocol/sdk-python
Project-URL: Issues, https://github.com/ctxprotocol/sdk-python/issues
Author-email: Context Protocol <team@ctxprotocol.com>
License-Expression: MIT
Keywords: ai,api-client,context-protocol,ctxprotocol,mcp,sdk,tools
Classifier: Development Status :: 4 - Beta
Classifier: Intended Audience :: Developers
Classifier: License :: OSI Approved :: MIT License
Classifier: Operating System :: OS Independent
Classifier: Programming Language :: Python :: 3
Classifier: Programming Language :: Python :: 3.10
Classifier: Programming Language :: Python :: 3.11
Classifier: Programming Language :: Python :: 3.12
Classifier: Programming Language :: Python :: 3.13
Classifier: Topic :: Scientific/Engineering :: Artificial Intelligence
Classifier: Topic :: Software Development :: Libraries :: Python Modules
Classifier: Typing :: Typed
Requires-Python: >=3.10
Requires-Dist: cryptography>=42.0.0
Requires-Dist: httpx>=0.27.0
Requires-Dist: pydantic>=2.0.0
Requires-Dist: pyjwt[crypto]>=2.8.0
Provides-Extra: dev
Requires-Dist: mypy>=1.10.0; extra == 'dev'
Requires-Dist: pytest-asyncio>=0.23.0; extra == 'dev'
Requires-Dist: pytest>=8.0.0; extra == 'dev'
Requires-Dist: ruff>=0.4.0; extra == 'dev'
Provides-Extra: fastapi
Requires-Dist: fastapi>=0.111.0; extra == 'fastapi'
Requires-Dist: starlette>=0.37.0; extra == 'fastapi'
